disruption_py/__init__.py
disruption_py/config.py
disruption_py/config.toml
disruption_py/core/__init__.py
disruption_py/core/physics_method/__init__.py
disruption_py/core/physics_method/caching.py
disruption_py/core/physics_method/decorator.py
disruption_py/core/physics_method/errors.py
disruption_py/core/physics_method/metadata.py
disruption_py/core/physics_method/params.py
disruption_py/core/physics_method/runner.py
disruption_py/core/retrieval_manager.py
disruption_py/core/utils/enums.py
disruption_py/core/utils/math.py
disruption_py/core/utils/misc.py
disruption_py/core/utils/shared_instance.py
disruption_py/data/README.md
disruption_py/data/cmod_ufo.csv
disruption_py/data/cmod_vde.csv
disruption_py/inout/__init__.py
disruption_py/inout/mds.py
disruption_py/inout/sql.py
disruption_py/machine/__init__.py
disruption_py/machine/cmod/__init__.py
disruption_py/machine/cmod/config.toml
disruption_py/machine/cmod/efit.py
disruption_py/machine/cmod/physics.py
disruption_py/machine/cmod/thomson.py
disruption_py/machine/d3d/__init__.py
disruption_py/machine/d3d/config.toml
disruption_py/machine/d3d/efit.py
disruption_py/machine/d3d/physics.py
disruption_py/machine/d3d/util.py
disruption_py/machine/east/__init__.py
disruption_py/machine/east/config.toml
disruption_py/machine/east/efit.py
disruption_py/machine/east/physics.py
disruption_py/machine/east/util.py
disruption_py/machine/generic/__init__.py
disruption_py/machine/generic/physics.py
disruption_py/machine/hbtep/__init__.py
disruption_py/machine/hbtep/config.toml
disruption_py/machine/hbtep/physics.py
disruption_py/machine/hbtep/util.py
disruption_py/machine/method_holders.py
disruption_py/machine/tokamak.py
disruption_py/settings/__init__.py
disruption_py/settings/log_settings.py
disruption_py/settings/nickname_setting.py
disruption_py/settings/output_setting.py
disruption_py/settings/retrieval_settings.py
disruption_py/settings/shotlist_setting.py
disruption_py/settings/time_setting.py
disruption_py/workflow.py
disruption_py-0.12.0.dist-info/METADATA
disruption_py-0.12.0.dist-info/WHEEL
disruption_py-0.12.0.dist-info/entry_points.txt
disruption_py-0.12.0.dist-info/licenses/LICENSE
disruption_py-0.12.0.dist-info/RECORD
