Metadata-Version: 2.4
Name: disruption-py
Version: 0.12.0
Summary: An open-source physics-based Scientific Framework for Disruption Analysis of Fusion Plasmas for AI/ML applications
License-Expression: MIT
License-File: LICENSE
Keywords: plasma physics,nuclear fusion,tokamak,disruptions
Author: Gregorio L. Trevisan
Author-email: gtrevisan@psfc.mit.edu
Maintainer: Gregorio L. Trevisan
Maintainer-email: gtrevisan@psfc.mit.edu
Requires-Python: >=3.11,<3.14
Classifier: Development Status :: 4 - Beta
Classifier: Environment :: Console
Classifier: Intended Audience :: Science/Research
Classifier: Natural Language :: English
Classifier: Operating System :: POSIX :: Linux
Classifier: Programming Language :: Python :: 3
Classifier: Topic :: Scientific/Engineering
Classifier: Topic :: Scientific/Engineering :: Physics
Classifier: Topic :: Scientific/Engineering :: Artificial Intelligence
Classifier: Topic :: Software Development :: Libraries :: Python Modules
Classifier: Topic :: Software Development :: Version Control :: Git
Requires-Dist: SQLAlchemy (>=2.0.0)
Requires-Dist: dynaconf (>=3.2.0)
Requires-Dist: loguru (>=0.7.0)
Requires-Dist: netcdf4 (>=1.7.0,<1.7.3)
Requires-Dist: numpy (>=1.26.0,<2.0.0)
Requires-Dist: pandas (>=2.2.0,<2.3.3)
Requires-Dist: pyodbc (>=5.2.0)
Requires-Dist: scipy (>=1.15.0)
Requires-Dist: tqdm (>=4.67.0)
Requires-Dist: xarray (>=2025.1.0)
Project-URL: Documentation, https://mit-psfc.github.io/disruption-py/
Project-URL: Homepage, https://disruptions.mit.edu/
Project-URL: Repository, https://github.com/MIT-PSFC/disruption-py/
